{"name": "Upstream", "permalink": "upstream-systems", "crunchbase_url": "http://www.crunchbase.com/company/upstream-systems", "homepage_url": "http://www.upstreamsystems.com", "blog_url": "", "blog_feed_url": "", "twitter_username": "upstreamglobal", "category_code": "other", "number_of_employees": 250, "founded_year": 2001, "founded_month": null, "founded_day": null, "deadpooled_year": null, "deadpooled_month": null, "deadpooled_day": null, "deadpooled_url": null, "tag_list": "mobile, marketing, mobile-advertising, mobile-marketing, gamification, revenue-generation, digital-marketing, marketing-software", "alias_list": "", "email_address": "info-uk@upstreamsystems.com", "phone_number": "+44 0207 307 7460", "description": "Digital Marketing  Technology Solutions", "created_at": "Mon Jun 01 19:15:53 UTC 2009", "updated_at": "Wed Apr 04 04:06:09 UTC 2012", "overview": "\u003Cp\u003EMore than 5 trillion ad impressions per year frustrate consumers and escalating use of personal data worries them. \u003C/p\u003E\n\n\u003Cp\u003EUpstream solves this problem of saturation vs. invasive targeting with our unique technology. \u003C/p\u003E\n\n\u003Cp\u003EOur marketing technology platform, MCS, can chew big data, provide profound analytics in real time and use machine learning algorithms to improve consumer purchase rates by 100% on average, adding more than $500 million to our clients\u2019 revenues in 40 countries.\u003C/p\u003E\n\n\u003Cp\u003E24 billion marketing messages have been exchanged through MCS with hundreds of millions of consumers in 23 languages. We\u2019ve built the strongest knowledge base in the industry and the ability to drive better content, context and real-time adjustments that result in more convincing sales messages.\u003C/p\u003E\n\n\u003Cp\u003EWe offer truly global coverage with offices in London, Redwood City, Rio de Janeiro, Singapore, Dubai, Athens, Bucharest and Rome.\u003C/p\u003E\n\n\u003Cp\u003EWE SWITCH CONSUMERS ON\u003C/p\u003E", "image":  {"available_sizes":    [[[150,       67],      "assets/images/resized/0009/5164/95164v2-max-150x150.jpg"],     [[250,       112],      "assets/images/resized/0009/5164/95164v2-max-250x250.jpg"],     [[450,       202],      "assets/images/resized/0009/5164/95164v2-max-450x450.jpg"]],   "attribution": null}, "products":  [], "relationships":  [{"is_past": false,    "title": "Co-Founder, CEO",    "person":     {"first_name": "Alex",      "last_name": "Vratskides",      "permalink": "alex-vratskides"}},   {"is_past": false,    "title": "SVP of Product Management",    "person":     {"first_name": "Assaf",      "last_name": "Baciu",      "permalink": "assaf-baciu"}},   {"is_past": false,    "title": "Vice President Business Development",    "person":     {"first_name": "Nikos",      "last_name": "Moraitakis",      "permalink": "nikos-moraitakis"}},   {"is_past": false,    "title": "Co-Founder, President",    "person":     {"first_name": "Marco",      "last_name": "Veremis",      "permalink": "marco-veremis"}},   {"is_past": false,    "title": "GM North American Operations",    "person":     {"first_name": "Mike",      "last_name": "Linnert",      "permalink": "mike-linnert"}},   {"is_past": false,    "title": "SVP, Global Sales ",    "person":     {"first_name": "Vu",      "last_name": "Nguyen",      "permalink": "vu-nguyen-2"}},   {"is_past": false,    "title": "COO",    "person":     {"first_name": "Simon",      "last_name": "Negus",      "permalink": "simon-negus"}},   {"is_past": false,    "title": "SVP, Innovation ",    "person":     {"first_name": "Guy",      "last_name": "Krief",      "permalink": "guy-krief"}},   {"is_past": false,    "title": "SVP, Finance ",    "person":     {"first_name": "Panos",      "last_name": "Martinis",      "permalink": "panos-martinis"}}], "competitions":  [], "providerships":  [], "total_money_raised": "\u20ac11M", "funding_rounds":  [{"round_code": "unattributed",    "source_url": "http://www.altassets.com/private-equity-news/article/nz15879.html",    "source_description": " Upstream raises 11m Euro growth capital",    "raised_amount": 11000000.0,    "raised_currency_code": "EUR",    "funded_year": 2009,    "funded_month": 5,    "funded_day": 27,    "investments":     [{"company": null,       "financial_org":        {"name": "TLcom Capital Partners",         "permalink": "tlcom-capital-partners"},       "person": null}]}], "investments":  [], "acquisition": null, "acquisitions":  [], "offices":  [{"description": "Upstream U.S. ",    "address1": "100 Marine Parkway",    "address2": "Suite 300",    "zip_code": "94065",    "city": "Redwood City ",    "state_code": "CA",    "country_code": "GBR",    "latitude": null,    "longitude": null},   {"description": "Upstream EMEA",    "address1": "Portland House",    "address2": "Bressenden Place",    "zip_code": "SW1E 5BH",    "city": "London",    "state_code": null,    "country_code": "GBR",    "latitude": null,    "longitude": null},   {"description": "Upstream Athens ",    "address1": "Kastorias 4, Gerakas",    "address2": "Attiki 15344",    "zip_code": "",    "city": "Athens",    "state_code": null,    "country_code": "GRC",    "latitude": null,    "longitude": null},   {"description": "Upstream Latin America ",    "address1": "Av. Luis Carlos Prestes, 180 Sala 301",    "address2": "Barra da Tijuca",    "zip_code": "CEP 22775-055",    "city": "Rio de Janeiro ",    "state_code": null,    "country_code": "BRA",    "latitude": null,    "longitude": null},   {"description": "Upstream UAE ",    "address1": "Al Thuraya Tower 1",    "address2": "Office 1901",    "zip_code": "",    "city": "Dubai ",    "state_code": null,    "country_code": "ARE",    "latitude": null,    "longitude": null},   {"description": "Upstream Italy ",    "address1": "Via Antonio Salandra 18",    "address2": "00187",    "zip_code": "",    "city": "Rome ",    "state_code": null,    "country_code": "ITA",    "latitude": null,    "longitude": null},   {"description": "Upstream Srl Romania",    "address1": "Str. Finlanda Nr. 8 ET 1, AP 2, Sector 1",    "address2": "",    "zip_code": "011776",    "city": "Bucharest",    "state_code": null,    "country_code": "ROM",    "latitude": null,    "longitude": null}], "milestones":  [{"description": "Upstream Adds Real-Time Personalisation to its Gamification Engine",    "stoned_year": 2011,    "stoned_month": 5,    "stoned_day": 25,    "source_url": "http://www.wirelessweek.com/News/2011/05/Business-Upstream-Gamification-New-Platform-Feature-Mobile-Content/",    "source_text": null,    "source_description": "Wireless Week ",    "stoneable_type": "Company",    "stoned_value": null,    "stoned_value_type": null,    "stoned_acquirer": null,    "stoneable":     {"name": "Upstream",      "permalink": "upstream-systems"}},   {"description": "Upstream Hires Vu Nguyen as SVP Global Sales ",    "stoned_year": 2011,    "stoned_month": 6,    "stoned_day": null,    "source_url": "http://mobilemarketingmagazine.com/content/upstream-hires-svp-global-sales",    "source_text": null,    "source_description": "Mobile Marketing ",    "stoneable_type": "Company",    "stoned_value": null,    "stoned_value_type": null,    "stoned_acquirer": null,    "stoneable":     {"name": "Upstream",      "permalink": "upstream-systems"}},   {"description": "Former Microsoft Partner, Simon Negus, Takes on Chief Operating Officer Role at Upstream ",    "stoned_year": 2011,    "stoned_month": 7,    "stoned_day": 20,    "source_url": "http://m.mobilemarketingmagazine.com/mobilemarketing/i/article/upstream-recruits-negus-microsoft",    "source_text": null,    "source_description": "Mobile Marketing ",    "stoneable_type": "Company",    "stoned_value": null,    "stoned_value_type": null,    "stoned_acquirer": null,    "stoneable":     {"name": "Upstream",      "permalink": "upstream-systems"}},   {"description": "Upstream Establishes Silicon Valley U.S. Headquarters to Drive Growth North American Expansion",    "stoned_year": 2011,    "stoned_month": 7,    "stoned_day": 27,    "source_url": "http://siliconvalley.rcrwireless.com/2011/07/26/upstream-drops-anchor-in-silicon-valley/",    "source_text": null,    "source_description": "RCR Silicon Valley ",    "stoneable_type": "Company",    "stoned_value": null,    "stoned_value_type": null,    "stoned_acquirer": null,    "stoneable":     {"name": "Upstream",      "permalink": "upstream-systems"}},   {"description": "Upstream Mobile Marketing Named as Top 50 Mobile Innovator",    "stoned_year": 2011,    "stoned_month": 9,    "stoned_day": 5,    "source_url": "http://corp.upstreamsystems.com/upstream-mobile-marketing-named-as-top-50-mobile-innovator",    "source_text": null,    "source_description": "Mobile Entertainment",    "stoneable_type": "Company",    "stoned_value": null,    "stoned_value_type": null,    "stoned_acquirer": null,    "stoneable":     {"name": "Upstream",      "permalink": "upstream-systems"}}], "ipo": null, "video_embeds":  [{"embed_code": "\u003Ciframe width=\"420\" height=\"315\" src=\"http://www.youtube.com/embed/sQ2IraGOpJQ\" frameborder=\"0\" allowfullscreen\u003E\u003C/iframe\u003E",    "description": "\u003Cp\u003EMarco Veremis, President of Upstream, interviewed by the BBC\u003C/p\u003E"},   {"embed_code": "\u003Ciframe width=\"560\" height=\"315\" src=\"http://www.youtube.com/embed/KPszooVDPfs\" frameborder=\"0\" allowfullscreen\u003E\u003C/iframe\u003E",    "description": "\u003Cp\u003EUpstream Switching Customers On\u003C/p\u003E"},   {"embed_code": "\u003Ciframe width=\"560\" height=\"315\" src=\"http://www.youtube.com/embed/gerr6QccZJE\" frameborder=\"0\" allowfullscreen\u003E\u003C/iframe\u003E",    "description": "\u003Cp\u003EUpstream\u0026#8217;s Marketing Communication Suite\u003C/p\u003E"},   {"embed_code": "\u003Ciframe width=\"420\" height=\"315\" src=\"http://www.youtube.com/embed/4AXLlH-KX-Y\" frameborder=\"0\" allowfullscreen\u003E\u003C/iframe\u003E",    "description": "\u003Cp\u003EMarco Veremis - Interviewed by CNN\u003C/p\u003E"}], "screenshots":  [{"available_sizes":     [[[79,        150],       "assets/images/resized/0017/5376/175376v2-max-150x150.jpg"],      [[132,        250],       "assets/images/resized/0017/5376/175376v2-max-250x250.jpg"],      [[237,        450],       "assets/images/resized/0017/5376/175376v2-max-450x450.jpg"]],    "attribution": null},   {"available_sizes":     [[[150,        106],       "assets/images/resized/0017/5378/175378v2-max-150x150.jpg"],      [[250,        177],       "assets/images/resized/0017/5378/175378v2-max-250x250.jpg"],      [[450,        319],       "assets/images/resized/0017/5378/175378v2-max-450x450.jpg"]],    "attribution": null},   {"available_sizes":     [[[30,        150],       "assets/images/resized/0017/9950/179950v2-max-150x150.jpg"],      [[50,        250],       "assets/images/resized/0017/9950/179950v2-max-250x250.jpg"],      [[91,        450],       "assets/images/resized/0017/9950/179950v2-max-450x450.jpg"]],    "attribution": null}], "external_links":  []}